README.md
setup.py
bookshops/__init__.py
bookshops.egg-info/PKG-INFO
bookshops.egg-info/SOURCES.txt
bookshops.egg-info/dependency_links.txt
bookshops.egg-info/entry_points.txt
bookshops.egg-info/requires.txt
bookshops.egg-info/top_level.txt
bookshops/all/__init__.py
bookshops/all/discogs/__init__.py
bookshops/all/discogs/discogsConnector.py
bookshops/all/discogs/discogsConnectorLiveTest.py
bookshops/all/discogs/discogsConnectorTest.py
bookshops/all/discogs/discogsScraper.py
bookshops/deDE/__init__.py
bookshops/deDE/buchlentner/__init__.py
bookshops/deDE/buchlentner/buchlentnerScraper.py
bookshops/deDE/buchlentner/test_end2end.py
bookshops/enEN/__init__.py
bookshops/esES/__init__.py
bookshops/esES/casadellibro/__init__.py
bookshops/esES/casadellibro/casadellibroScraper.py
bookshops/esES/casadellibro/test_end2end.py
bookshops/frFR/__init__.py
bookshops/frFR/decitre/__init__.py
bookshops/frFR/decitre/decitreScraper.py
bookshops/frFR/decitre/test_end2end.py
bookshops/frFR/librairiedeparis/__init__.py
bookshops/frFR/librairiedeparis/librairiedeparisScraper.py
bookshops/frFR/librairiedeparis/test_end2end.py
bookshops/odslookup/__init__.py
bookshops/odslookup/odf2py.py
bookshops/odslookup/ods2csv2py.py
bookshops/odslookup/odslookup.py
bookshops/odslookup/odssettings.py
bookshops/odslookup/odsutils.py
bookshops/odslookup/tests/__init__.py
bookshops/odslookup/tests/testcsv2py.py
bookshops/odslookup/tests/testodslookup.py
bookshops/odslookup/tests/testodsutils.py
bookshops/utils/__init__.py
bookshops/utils/baseScraper.py
bookshops/utils/decorators.py
bookshops/utils/scraperUtils.py
bookshops/utils/testScraperBase.py