Metadata-Version: 1.1
Name: bookshops
Version: 0.2.1
Summary: Get book information (isbn or search) from real bookstores.
Home-page: https://gitlab.com/vindarel/bookshops
Author: vindarel
Author-email: ehvince@mailz.org
License: GNU LGPLv3
Keywords: bookshop bookstore library book isbn ean webscraping
Platform: UNKNOWN
Classifier: Environment :: Web Environment
Classifier: Environment :: Console
Classifier: Environment :: Plugins
Classifier: Intended Audience :: Developers
Classifier: Intended Audience :: End Users/Desktop
Classifier: License :: OSI Approved :: GNU Library or Lesser General Public License (LGPL)
Classifier: Topic :: Utilities
Classifier: Programming Language :: Python :: 2.7
Classifier: Topic :: Internet
Classifier: Topic :: Software Development :: Libraries
